[
  {
    "id": "review-theater-program-review-ay-2021-2022-0",
    "source": "review",
    "sourceId": "theater-program-review-ay-2021-2022",
    "title": "Theater Program Review AY 2021-2022 (Part 1)",
    "text": "College of the Siskiyous Annual Program Review- Theatre Arts AY 2021-22\n1. Describe annual progress / changes / events in the program.\nWhile the Covid-19 pandemic upended many of the theater program’s plans for the academic\nyear we able to mitigate some of its effects despite the wide spread disruption it caused. As\nmentioned in previous program reviews, the theater staff and faculty have a dynamic and\ndiverse skill set allowing us to be very adaptive to challenges, even world-wide events.\nThe Theater program remains committed to 3 key areas; recruitment, retention, and award\ncompletion, which keeps us in alignment with the College of the Siskiyou’s institutional goals.\nRecruitment\nEven though, over the years, we have created strong relationships with local high schools and\nK-12 regional arts programs which has resulted in a steady increase in our student head counts,\nour recruitment efforts have been limited due to Covid-19 restrictions.\nAs high school performing arts teachers struggle to keep their programs alive while they adhere\nto necessary social distancing protocols we have attempted to reach out and offer support by\ndoing the following;\nEmailed high school arts educators offering support\nReached out to high students with audition invitations for both Fall 2020 and Spring\n2021 Zoom productions\nRetention and Degree Completion\nOver the years, we have been able to continue to have good retention numbers largely due to\nproducing diverse and engaging productions which keep students attracted to the program.\nAlso our established transfer relationship with SOU as well as our participation in the Kennedy\nCenter American College Theater Festival, helps to create a viable and visible road to degree\ncompletion.\nWe have offered “Zoom” productions in both the Fall 2020 and Spring 2021 semesters\nin and attempt to keep students engaged.\nWe have moved courses required for theater degrees and certificates to either online or\nhybrid formats in an effort to provide a means towards degree completion.\n2. Describe progress on assessing SLOs and PLOs for the program.\nNo progress due to institutional lack of commitment.\n\n-- 1 of 3 --",
    "metadata": {
      "year": 2021,
      "reviewType": "Annual"
    },
    "tags": [
      "review",
      "annual",
      "year-2021"
    ],
    "tokenCount": 539
  },
  {
    "id": "review-theater-program-review-ay-2021-2022-1",
    "source": "review",
    "sourceId": "theater-program-review-ay-2021-2022",
    "title": "Theater Program Review AY 2021-2022 (Part 2)",
    "text": "College of the Siskiyous Annual Program Review- Theatre Arts AY 2021-22\n3. Discuss any support or obstacles encountered by the program.\nMoving classes to online and hybrid formats\nThe Covid-19 pandemic necessitated moving classes to either hybrid or online format which,\nlucky for the theater program, was one of our long-term goals. In fact, this year we were able to\nteach all of our classes in this manner which helped to mitigate some of the student attrition\ndue to the disruption of face to face instruction.\nWe were also able to successfully offer all “Zoom” productions in both semesters;\nFall 2020 “Shakespeare’s Greatest Hits”\nSpring 2021 “ Night Night Roger Roger”\nHiring of Adjunct Theater Instructor\nThis year we were fortunate to be able to hire an Adjunct Theater Instructor, Kitty Keim, who\nwas able to adapt to teaching both acting classes and directing each of our productions via\nZoom.\nWe have been proactive in taking advantage of opportunities. We have several talented\nteachers able to teach at the non-credit level so we have begun to create non-credit classes and\ncertificates which has led to a sharp increase in K-12 students and non-traditional students\nparticipating with our program, leading to increases in FTEs.\nIncrease our Non-Credit course offerings\nTo better serve both our degree seeking students and community members seeking enrichment\nthe Theater program is exploring adding a series of non-credit classes to either; accompany\ncredit courses so that community members can experience a more rigorous educational\nenvironment, or augment already existing credit courses to better prepare degree seeking\nstudents.\n4. Describe program budgetary needs or implications.\nRestore Theater Performance Instructor\nWhile the single full-time faculty member has volunteered to teach in overload since 2011,\nlargely to insure that students achieve Theater degrees and certificates, this has led to the delay\nof the creation of an AA in Technical Theater, and other important curricular development. The\nfull-time faculty member must serve as stage director, technical director, and set and lighting\n\n-- 2 of 3 --\n\nCollege of the Siskiyous Annual Program Review- Theatre Arts AY 2021-22\ndesigner for all productions pertaining to traditional tranfer level courses. The current faculty\nmember does possess all of the required skills to perform all of these roles but it’s not possible\nto perform them all at the same time. Over the past several years an attempt has been made to\nhire adjunct instructors to help teach the required courses for the various theater degreees but\nthis has proven to be ineffective. The region simply does not have a significant pool of qualified\ninstructors.\nBased on this evidence it is strongly recommended that the College of the Siskiyous hire\nanother full-time theater faculty to teach classes in performance and share the management\ntheater program. Please see CQIP 1.\n\n-- 3 of 3 --",
    "metadata": {
      "year": 2021,
      "reviewType": "Annual"
    },
    "tags": [
      "review",
      "annual",
      "year-2021"
    ],
    "tokenCount": 735
  }
]